antares/__init__.py
antares/apps/__init__.py
antares/apps/accounting/__init__.py
antares/apps/accounting/admin.py
antares/apps/accounting/apps.py
antares/apps/accounting/constants.py
antares/apps/accounting/urls.py
antares/apps/accounting/api/__init__.py
antares/apps/accounting/api/api_account_type_view.py
antares/apps/accounting/api/api_client_view.py
antares/apps/accounting/api/api_concept_type_view.py
antares/apps/accounting/api/api_period_view.py
antares/apps/accounting/console/__init__.py
antares/apps/accounting/console/account_console.py
antares/apps/accounting/exceptions/__init__.py
antares/apps/accounting/exceptions/missing_account_header_information_exception.py
antares/apps/accounting/exceptions/negative_amount_exception.py
antares/apps/accounting/locale/en/LC_MESSAGES/django.mo
antares/apps/accounting/locale/en/LC_MESSAGES/django.po
antares/apps/accounting/locale/es/LC_MESSAGES/django.mo
antares/apps/accounting/locale/es/LC_MESSAGES/django.po
antares/apps/accounting/manager/__init__.py
antares/apps/accounting/manager/account_manager.py
antares/apps/accounting/manager/charges_manager.py
antares/apps/accounting/manager/gl_manager.py
antares/apps/accounting/manager/tests/__init__.py
antares/apps/accounting/manager/tests/account_manager_test.py
antares/apps/accounting/migrations/0001_initial.py
antares/apps/accounting/migrations/0002_auto_20180624_1759.py
antares/apps/accounting/migrations/0003_auto_20190629_1936.py
antares/apps/accounting/migrations/0004_auto_20200131_0956.py
antares/apps/accounting/migrations/0005_auto_20200131_1445.py
antares/apps/accounting/migrations/0006_auto_20200131_1446.py
antares/apps/accounting/migrations/0007_interestdefinition_penaltydefinition.py
antares/apps/accounting/migrations/0008_accountcharge.py
antares/apps/accounting/migrations/0009_auto_20200208_2236.py
antares/apps/accounting/migrations/0010_auto_20200208_2237.py
antares/apps/accounting/migrations/0011_auto_20200208_2248.py
antares_apps-0.0.5.dist-info/LICENSE
antares_apps-0.0.5.dist-info/METADATA
antares_apps-0.0.5.dist-info/WHEEL
antares_apps-0.0.5.dist-info/top_level.txt
antares_apps-0.0.5.dist-info/zip-safe
antares_apps-0.0.5.dist-info/RECORD
