Metadata-Version: 2.1
Name: antares-apps
Version: 0.0.5
Summary: Antares Apps Module
Home-page: http://antares.surfertank.com/
Author: Leonardo Javier Belén
Author-email: leobelen@gmail.com
License: DUAL
Download-URL: https://bitbucket.org/leobelen/antares-apps/get/0.0.5.tar.gz
Keywords: management,infrastructure
Platform: UNKNOWN
Classifier: Development Status :: 3 - Alpha
Classifier: Environment :: Web Environment
Classifier: Framework :: Django
Classifier: Intended Audience :: Developers
Classifier: Operating System :: OS Independent
Classifier: Programming Language :: Python
Classifier: Programming Language :: Python :: 3
Classifier: Programming Language :: Python :: 3.5
Classifier: Programming Language :: Python :: 3.6
Classifier: Topic :: Internet :: WWW/HTTP
Classifier: Topic :: Internet :: WWW/HTTP :: Dynamic Content
Requires-Dist: Django (>=2.2.9)
Requires-Dist: defusedxml (>=0.5.0)
Requires-Dist: django-allauth (>=0.32.0)
Requires-Dist: django-angular (>=0.8.4)
Requires-Dist: django-bower (>=5.2.0django-braces>=1.11.0)
Requires-Dist: django-ckeditor (>=5.2.2)
Requires-Dist: django-datatables-view (>=1.14.0)
Requires-Dist: django-enumfields (>=0.9.0)
Requires-Dist: django-extensions (>=1.7.8)
Requires-Dist: django-fastcgi (>=0.0.1)
Requires-Dist: django-filter (>=1.0.2)
Requires-Dist: django-libs (>=1.67.12)
Requires-Dist: django-markdown-app (>=0.9.1)
Requires-Dist: django-markdown-deux (>=1.0.5)
Requires-Dist: django-mptt (>=0.8.7)
Requires-Dist: django-pipeline (>=1.6.12)
Requires-Dist: djangorestframework (>=3.6.2)
Requires-Dist: google-api-python-client (>=1.6.2)
Requires-Dist: googlemaps (>=2.4.6)
Requires-Dist: Js2Py (>=0.44)
Requires-Dist: Markdown (>=2.6.8)
Requires-Dist: markdown2 (>=2.3.4)
Requires-Dist: MarkupSafe (>=1.0)
Requires-Dist: python-dateutil (>=2.6.0)
Requires-Dist: python-slugify (>=1.2.4)
Requires-Dist: tox (>=2.7.0)
Requires-Dist: whitenoise (>=3.3.0)
